wxpayzhiyan
