Metadata-Version: 2.1
Name: wxpayzhiyan
Version: 1.1.4
Summary: logten python package
Home-page: UNKNOWN
Author: 
Author-email: 
License: UNKNOWN
Keywords: pipeline
Platform: UNKNOWN
Classifier: Programming Language :: Python :: 3
Classifier: Programming Language :: Python :: 3.6
